[
  {
    "id": 1,
    "nome": "Risotto allo Zafferano",
    "categoria": "Primi",
    "descrizione": "Carnaroli mantecato con zafferano puro di Navelli e foglia d'oro 23k.",
    "prezzo": 24,
    "tempo": 22,
    "immagine": "risotto-allo-zafferano.webp",
    "veg": true
  },
  {
    "id": 2,
    "nome": "Ossobuco alla Milanese",
    "categoria": "Secondi",
    "descrizione": "Stinco di vitello brasato 6 ore, gremolada di limone e prezzemolo.",
    "prezzo": 32,
    "tempo": 30,
    "immagine": "ossobuco-alla-milanese.jpg",
    "veg": false
  },
  {
    "id": 3,
    "nome": "Tiramisu d'Autore",
    "categoria": "Dolci",
    "descrizione": "Mascarpone montato a mano, savoiardi al caffe espresso e cacao Valrhona.",
    "prezzo": 12,
    "tempo": 8,
    "immagine": "tiramisu-d-autore.jpg",
    "veg": true
  },
  {
    "id": 4,
    "nome": "Tagliere della Casa",
    "categoria": "Antipasti",
    "descrizione": "Salumi selezionati, formaggi affinati, giardiniera croccante e pane caldo.",
    "prezzo": 18,
    "tempo": 12,
    "immagine": "tagliere-della-casa.jpg",
    "veg": false
  },
  {
    "id": 5,
    "nome": "Branzino agli Agrumi",
    "categoria": "Secondi",
    "descrizione": "Filetto di branzino scottato, salsa agli agrumi e verdure di stagione.",
    "prezzo": 29,
    "tempo": 24,
    "immagine": "branzino-agli-agrumi.webp",
    "veg": false
  },
  {
    "id": 6,
    "nome": "Calice Nebbiolo",
    "categoria": "Vini",
    "descrizione": "Rosso elegante, tannino fine, profumi di viola, spezie e piccoli frutti.",
    "prezzo": 10,
    "tempo": 3,
    "immagine": "calice-nebbiolo.avif",
    "veg": true
  },
  {
    "id": 7,
    "nome": "Spaghettone Cacio e Pepe",
    "categoria": "Primi",
    "descrizione": "Pasta trafilata al bronzo, pecorino romano DOP e pepe nero tostato.",
    "prezzo": 18,
    "tempo": 16,
    "immagine": "spaghettone-cacio-e-pepe.avif",
    "veg": true
  },
  {
    "id": 8,
    "nome": "Ravioli di Ricotta e Limone",
    "categoria": "Primi",
    "descrizione": "Pasta fresca ripiena, burro alle erbe, scorza di limone e salvia croccante.",
    "prezzo": 21,
    "tempo": 20,
    "immagine": "ravioli-di-ricotta-e-limone.jpg",
    "veg": true
  },
  {
    "id": 9,
    "nome": "Pappardelle al Ragu Bianco",
    "categoria": "Primi",
    "descrizione": "Pappardelle fatte in casa con ragu bianco di vitello e rosmarino.",
    "prezzo": 23,
    "tempo": 24,
    "immagine": "pappardelle-al-ragu-bianco.webp",
    "veg": false
  },
  {
    "id": 10,
    "nome": "Gnocchi al Pomodoro Arrosto",
    "categoria": "Primi",
    "descrizione": "Gnocchi di patate, crema di pomodoro arrosto, basilico e stracciatella.",
    "prezzo": 19,
    "tempo": 18,
    "immagine": "gnocchi-al-pomodoro-arrosto.webp",
    "veg": true
  },
  {
    "id": 11,
    "nome": "Lasagnetta Verde",
    "categoria": "Primi",
    "descrizione": "Sfoglia agli spinaci, besciamella leggera, verdure di stagione e Parmigiano.",
    "prezzo": 20,
    "tempo": 25,
    "immagine": "lasagnetta-verde.jpg",
    "veg": true
  },
  {
    "id": 12,
    "nome": "Filetto al Pepe Verde",
    "categoria": "Secondi",
    "descrizione": "Filetto di manzo scottato, salsa al pepe verde e patate novelle.",
    "prezzo": 36,
    "tempo": 28,
    "immagine": "filetto-al-pepe-verde.webp",
    "veg": false
  },
  {
    "id": 13,
    "nome": "Polpo Croccante",
    "categoria": "Secondi",
    "descrizione": "Polpo alla piastra, crema di patate affumicate e olive taggiasche.",
    "prezzo": 31,
    "tempo": 26,
    "immagine": "polpo-croccante.jpg",
    "veg": false
  },
  {
    "id": 14,
    "nome": "Cotoletta alla Milanese",
    "categoria": "Secondi",
    "descrizione": "Costoletta di vitello dorata nel burro chiarificato con insalata di campo.",
    "prezzo": 34,
    "tempo": 30,
    "immagine": "cotoletta-alla-milanese.webp",
    "veg": false
  },
  {
    "id": 15,
    "nome": "Melanzana alla Parmigiana",
    "categoria": "Secondi",
    "descrizione": "Melanzane fritte leggere, pomodoro San Marzano, basilico e mozzarella.",
    "prezzo": 22,
    "tempo": 24,
    "immagine": "melanzana-alla-parmigiana.webp",
    "veg": true
  },
  {
    "id": 16,
    "nome": "Guancia Brasata",
    "categoria": "Secondi",
    "descrizione": "Guancia di manzo cotta lentamente, fondo al vino rosso e purea morbida.",
    "prezzo": 33,
    "tempo": 32,
    "immagine": "guancia-brasata.webp",
    "veg": false
  },
  {
    "id": 17,
    "nome": "Panna Cotta alla Vaniglia",
    "categoria": "Dolci",
    "descrizione": "Panna cotta morbida con vaniglia Bourbon e coulis di frutti rossi.",
    "prezzo": 10,
    "tempo": 6,
    "immagine": "panna-cotta-alla-vaniglia.jpg",
    "veg": true
  },
  {
    "id": 18,
    "nome": "Crostata al Pistacchio",
    "categoria": "Dolci",
    "descrizione": "Frolla al burro, crema al pistacchio e granella tostata.",
    "prezzo": 12,
    "tempo": 7,
    "immagine": "crostata-al-pistacchio.jpg",
    "veg": true
  },
  {
    "id": 19,
    "nome": "Millefoglie alla Crema",
    "categoria": "Dolci",
    "descrizione": "Sfoglia caramellata, crema diplomatica e frutti di stagione.",
    "prezzo": 13,
    "tempo": 9,
    "immagine": "millefoglie-alla-crema.webp",
    "veg": true
  },
  {
    "id": 20,
    "nome": "Calice Franciacorta Brut",
    "categoria": "Vini",
    "descrizione": "Bollicina metodo classico, fresca e minerale, ideale per antipasti e pesce.",
    "prezzo": 12,
    "tempo": 3,
    "immagine": "calice-franciacorta-brut.webp",
    "veg": true
  },
  {
    "id": 21,
    "nome": "Calice Chianti Classico",
    "categoria": "Vini",
    "descrizione": "Rosso toscano equilibrato, note di ciliegia, spezie dolci e finale sapido.",
    "prezzo": 11,
    "tempo": 3,
    "immagine": "calice-chianti-classico.jpg",
    "veg": true
  },
  {
    "id": 22,
    "nome": "Carpaccio di Manzo",
    "categoria": "Antipasti",
    "descrizione": "Fettine sottili di manzo, rucola selvatica, scaglie di Parmigiano e limone.",
    "prezzo": 17,
    "tempo": 10,
    "immagine": "carpaccio-di-manzo.jpg",
    "veg": false
  },
  {
    "id": 23,
    "nome": "Burrata e Pomodorini",
    "categoria": "Antipasti",
    "descrizione": "Burrata pugliese, pomodorini confit, basilico fresco e olio extravergine.",
    "prezzo": 15,
    "tempo": 8,
    "immagine": "burrata-e-pomodorini.jpg",
    "veg": true
  },
  {
    "id": 24,
    "nome": "Fiori di Zucca Ripieni",
    "categoria": "Antipasti",
    "descrizione": "Fiori di zucca croccanti con ricotta, menta e salsa leggera al pomodoro.",
    "prezzo": 16,
    "tempo": 14,
    "immagine": "fiori-di-zucca-ripieni.jpg",
    "veg": true
  }
]
